MAOuladlinear_regression/MAOuladlinear_regression.py
MAOuladlinear_regression/__init__.py
MAOuladlinear_regression/regression.py
linear_regression/__init__.py
linear_regression/regression.py
MAOuladlinear_regression-1.0.0.dist-info/LICENSE.txt
MAOuladlinear_regression-1.0.0.dist-info/METADATA
MAOuladlinear_regression-1.0.0.dist-info/WHEEL
MAOuladlinear_regression-1.0.0.dist-info/top_level.txt
MAOuladlinear_regression-1.0.0.dist-info/RECORD
